rio_cloudmask/__init__.py
rio_cloudmask/equations.py
rio_cloudmask/scripts/__init__.py
rio_cloudmask/scripts/cli.py
rio_cloudmask-0.3.0.dist-info/DESCRIPTION.rst
rio_cloudmask-0.3.0.dist-info/METADATA
rio_cloudmask-0.3.0.dist-info/RECORD
rio_cloudmask-0.3.0.dist-info/WHEEL
rio_cloudmask-0.3.0.dist-info/entry_points.txt
rio_cloudmask-0.3.0.dist-info/metadata.json
rio_cloudmask-0.3.0.dist-info/top_level.txt
