Metadata-Version: 2.0
Name: rio-cloudmask
Version: 0.3.0
Summary: Cloud masking plugin for rasterio
Home-page: https://github.com/mapbox/rio-cloudmask
Author: Matthew Perry
Author-email: perrygeo@gmail.com
License: MIT
Platform: UNKNOWN
Classifier: Development Status :: 4 - Beta
Classifier: Intended Audience :: Developers
Classifier: Intended Audience :: Science/Research
Classifier: License :: OSI Approved :: MIT License
Classifier: Programming Language :: Cython
Classifier: Programming Language :: Python :: 2.7
Classifier: Programming Language :: Python :: 3.4
Classifier: Programming Language :: Python :: 3.5
Classifier: Programming Language :: Python :: 2
Classifier: Programming Language :: Python :: 3
Classifier: Topic :: Multimedia :: Graphics :: Graphics Conversion
Classifier: Topic :: Scientific/Engineering :: GIS
Requires-Dist: click
Requires-Dist: rasterio
Requires-Dist: rio-mucho
Requires-Dist: scipy
Provides-Extra: test
Requires-Dist: codecov; extra == 'test'
Requires-Dist: pytest; extra == 'test'
Requires-Dist: pytest-cov; extra == 'test'
